faerun/__init__.py
faerun/faerun.py
faerun/plot.py
faerun/template_default.j2
faerun/template_reaction_smiles.j2
faerun/template_smiles.j2
faerun/template_url_image.j2
faerun/web.py
faerun/assets/index_static.html
faerun-0.4.7.dist-info/LICENSE
faerun-0.4.7.dist-info/METADATA
faerun-0.4.7.dist-info/WHEEL
faerun-0.4.7.dist-info/top_level.txt
faerun-0.4.7.dist-info/RECORD
