Metadata-Version: 2.1
Name: faerun
Version: 0.4.7
Summary: A python package for generating interactive views of chemical spaces.
Home-page: https://github.com/reymond-group/faerun-python
Author: Daniel Probst
Requires-Python: >=3
License-File: LICENSE
Requires-Dist: matplotlib (>=3.0.2)
Requires-Dist: Jinja2 (>=2.10)
Requires-Dist: ujson (>=1.35)
Requires-Dist: numpy (>=1.15.4)
Requires-Dist: colour (>=0.1.5)
Requires-Dist: CherryPy (>=18.1.0)
Requires-Dist: pandas (>=0.24.2)
Provides-Extra: dev
Requires-Dist: pytest ; extra == 'dev'
